sltk/__init__.py
sltk/sltk.py
sltk-0.5.dist-info/DESCRIPTION.rst
sltk-0.5.dist-info/METADATA
sltk-0.5.dist-info/RECORD
sltk-0.5.dist-info/WHEEL
sltk-0.5.dist-info/metadata.json
sltk-0.5.dist-info/top_level.txt
