Metadata-Version: 2.0
Name: sltk
Version: 0.5
Summary: Spoken Language Toolkit
Home-page: http://github.com/nickdepinet/sltk
Author: Nick Depinet
Author-email: depinetnick@gmail.com
License: MIT
Platform: UNKNOWN
Requires-Dist: python-speech-features
